ollama_batch-0.1.3.dist-info/METADATA
ollama_batch-0.1.3.dist-info/WHEEL
ollama_batch-0.1.3.dist-info/entry_points.txt
ollama_batch-0.1.3.dist-info/licenses/LICENSE.md
ollama_batch/__init__.py
ollama_batch/__version__.py
ollama_batch/ollama_batch.py
ollama_batch-0.1.3.dist-info/RECORD
