Metadata-Version: 2.1
Name: ollama-batch
Version: 0.1.3
Summary: Run text LLM prompts over a list of texts
Keywords: ai,llm,ollama
Author-Email: Emilio Mariscal <emi.mariscal.dev@gmail.com>
License: AGPL
Classifier: Topic :: Utilities
Classifier: Programming Language :: Python :: 3
Classifier: Programming Language :: Python :: 3.10
Classifier: Programming Language :: Python :: 3.11
Project-URL: homepage, https://github.com/emi420/ollama-batch
Project-URL: documentation, https://github.com/emi420/ollama-batch
Project-URL: repository, https://github.com/emi420/ollama-batch
Requires-Python: >=3.10
Requires-Dist: ollama>=0.3.3
Requires-Dist: pillow>=11.3.0
